expden/__init__.py
expden/core.py
expden-0.1.3.dist-info/LICENSE
expden-0.1.3.dist-info/METADATA
expden-0.1.3.dist-info/WHEEL
expden-0.1.3.dist-info/RECORD
