Metadata-Version: 2.1
Name: expden
Version: 0.1.3
Summary: Library to compute the experienced density
License: MIT
Author: Nico Forteza 
Author-email: nicoforteza@gmail.com
Maintainer: Nico Forteza 
Maintainer-email: nicoforteza@gmail.com
Requires-Python: >=3.9.0,<4.0.0
Classifier: License :: OSI Approved :: MIT License
Classifier: Programming Language :: Python :: 3
Classifier: Programming Language :: Python :: 3.9
Classifier: Programming Language :: Python :: 3.10
Classifier: Programming Language :: Python :: 3.11
Classifier: Programming Language :: Python :: 3.12
Classifier: Programming Language :: Python :: 3.13
Requires-Dist: geocube (==0.4.0)
Requires-Dist: geopandas (==0.12.1)
Requires-Dist: numba (==0.56.4)
Requires-Dist: rioxarray (==0.13.1)
Requires-Dist: xarray-spatial (==0.3.5)
